[
  {
    "id": "tSrr6L3ZtzA",
    "title": "**Silver Price** New CRITICAL Facts YOU Must Hear - (Gold and Iran NEWS Update too)",
    "thumbnail": "https://i.ytimg.com/vi/tSrr6L3ZtzA/hqdefault.jpg",
    "channel": "Rons Basement",
    "channel_id": "UC7KRV9tVt7JqaSO3t6ifAsA",
    "published_at": "2026-03-02T00:22:36Z",
    "category": "Precious Metals",
    "duration_iso": "PT34M14S",
    "duration_minutes": 34.233333333333334,
    "url": "https://www.youtube.com/watch?v=tSrr6L3ZtzA",
    "tags": []
  },
  {
    "id": "Ez5Nd8vgFEw",
    "title": "SILVER PRICE ALERT: This is Going To Be HUGE!",
    "thumbnail": "https://i.ytimg.com/vi/Ez5Nd8vgFEw/hqdefault.jpg",
    "channel": "Wall Street Bullion",
    "channel_id": "UCXWoMTRWJTIZwUblljo5aDQ",
    "published_at": "2026-03-01T23:30:10Z",
    "category": "Precious Metals",
    "duration_iso": "PT12M13S",
    "duration_minutes": 12.216666666666667,
    "url": "https://www.youtube.com/watch?v=Ez5Nd8vgFEw",
    "tags": [
      "silver",
      "gold",
      "silversqueeze",
      "preciousmetals",
      "Reddit",
      "Miner",
      "housing crash",
      "housing crash 2021",
      "bitcoin",
      "real estate investing",
      "mortgage",
      "rates",
      "housing bubble",
      "housing market 2021",
      "housing market 2021 forecast",
      "deflation",
      "mortgage forbearance",
      "mortgage rates",
      "deflation 2021",
      "mortgage interest rates",
      "wall street silver",
      "silver raid",
      "LBMA",
      "interest rates",
      "Federal Reserve",
      "Fed",
      "Central Banks",
      "Comex",
      "wallstreetsilver",
      "inflation",
      "hyperinflation"
    ]
  },
  {
    "id": "vpTKLRQiEHU",
    "title": "SILVER PRICE NEWS ALERT - BUCKLE UP",
    "thumbnail": "https://i.ytimg.com/vi/vpTKLRQiEHU/hqdefault.jpg",
    "channel": "Silver Dragons",
    "channel_id": "UCucqfNRyBkieAop_LDUqHEg",
    "published_at": "2026-03-01T23:25:23Z",
    "category": "Precious Metals",
    "duration_iso": "PT31M19S",
    "duration_minutes": 31.316666666666666,
    "url": "https://www.youtube.com/watch?v=vpTKLRQiEHU",
    "tags": [
      "silver price update",
      "silver price silver price alert",
      "silver new",
      "silver news alert",
      "silver alert",
      "silver news update",
      "breaking silver news",
      "silver price up",
      "silver price down",
      "silver price",
      "silver price news",
      "silver news",
      "silver price soaring",
      "silver price new all time high",
      "silver all time high",
      "silver price all time high",
      "gold price new high",
      "gold price prediction",
      "gold price update",
      "gold update",
      "gold price forecast",
      "silver",
      "gold",
      "precious metals",
      "silver coins",
      "coins",
      "coin"
    ]
  },
  {
    "id": "WV_prQ6K8yU",
    "title": "Comex Gold Delivery Was Discouraged From The Beginning",
    "thumbnail": "https://i.ytimg.com/vi/WV_prQ6K8yU/hqdefault.jpg",
    "channel": "Arcadia Economics",
    "channel_id": "UC0xbkSGGxkI4AVp0BQRjnAA",
    "published_at": "2026-03-01T22:45:06Z",
    "category": "Precious Metals",
    "duration_iso": "PT7M8S",
    "duration_minutes": 7.133333333333334,
    "url": "https://www.youtube.com/watch?v=WV_prQ6K8yU",
    "tags": [
      "arcadia economics",
      "brics",
      "chris marcus",
      "comex",
      "de-dollarization",
      "dollar index",
      "donald trump",
      "federal reserve",
      "gold",
      "gold and silver",
      "gold price",
      "inflation",
      "interest rates",
      "precious metals",
      "silver",
      "silver bullion",
      "silver chart",
      "silver forecast",
      "silver investing",
      "silver manipulation",
      "silver market",
      "silver mining",
      "silver price",
      "silver price forecast",
      "silver price prediction",
      "silver stocks",
      "silver supply",
      "silver trading",
      "stock market",
      "the big silver short",
      "the unit",
      "David Morgan"
    ]
  },
  {
    "id": "Pti76j6BToE",
    "title": "Rick Rule Perfectly Called Silver Crash, Here\u2019s What \u2018Goes Crazy\u2019 Next",
    "thumbnail": "https://i.ytimg.com/vi/Pti76j6BToE/hqdefault.jpg",
    "channel": "David Lin",
    "channel_id": "UClBMLpP3UHXLmgEypMmXPuA",
    "published_at": "2026-03-01T22:25:55Z",
    "category": "General Financial Investing and Speculation",
    "duration_iso": "PT48M9S",
    "duration_minutes": 48.15,
    "url": "https://www.youtube.com/watch?v=Pti76j6BToE",
    "tags": [
      "david lin",
      "the david lin report",
      "david lin youtube",
      "david lin finance",
      "david lin investing",
      "david lin trading",
      "david lin economics",
      "economics",
      "finance",
      "business",
      "macroeconomics",
      "trading",
      "investing",
      "financial news",
      "finance news",
      "economics news",
      "business news",
      "economy",
      "rick rule",
      "rick rule investing",
      "battery metals",
      "recession",
      "stocks",
      "nasdaq",
      "sp500",
      "mining",
      "mining stocks",
      "inflation",
      "battle bank",
      "oil",
      "energy",
      "federal reserve",
      "the fed",
      "dollar",
      "gold",
      "silver",
      "gold rally",
      "minerals",
      "gold price",
      "iran"
    ]
  },
  {
    "id": "iDJF-xds8ZA",
    "title": "SILVER DEALER REVEALS HIS PICKS BEFORE A SILVER PRICE EXPLOSION! \ud83d\ude80",
    "thumbnail": "https://i.ytimg.com/vi/iDJF-xds8ZA/hqdefault.jpg",
    "channel": "Yankee Stacking",
    "channel_id": "UCSlo5dl8jvbmpJi-zcbqq6w",
    "published_at": "2026-03-01T19:55:00Z",
    "category": "Precious Metals",
    "duration_iso": "PT18M54S",
    "duration_minutes": 18.9,
    "url": "https://www.youtube.com/watch?v=iDJF-xds8ZA",
    "tags": [
      "Iran",
      "tariffs",
      "war",
      "what silver should I buy",
      "silver price",
      "how to sell silver",
      "how to buy silver",
      "how to sell gold",
      "silver spot price",
      "buying silver",
      "should I buy silver",
      "how high will silver go",
      "why silver is going down",
      "why is silver going down",
      "why is silver going up",
      "is buying silver coins worth it",
      "selling silver",
      "inflation",
      "gold price",
      "silver premiums",
      "silver eagle",
      "what is an ounce of silver worth",
      "silver bar",
      "silver coin",
      "silver rounds",
      "silver",
      "gold",
      "precious metals",
      "fed"
    ]
  },
  {
    "id": "RnjgLlQTMf0",
    "title": "Why Every AI Skill You Learned 6 Months Ago Is Already Wrong (And What Is Replacing Them)",
    "thumbnail": "https://i.ytimg.com/vi/RnjgLlQTMf0/hqdefault.jpg",
    "channel": "AI News & Strategy Daily | Nate B Jones",
    "channel_id": "UC0C-17n9iuUQPylguM1d-lQ",
    "published_at": "2026-03-01T19:00:20Z",
    "category": "Artificial Intelligence",
    "duration_iso": "PT28M44S",
    "duration_minutes": 28.733333333333334,
    "url": "https://www.youtube.com/watch?v=RnjgLlQTMf0",
    "tags": [
      "AI strategy",
      "frontier operations",
      "AI skills",
      "future of work",
      "AI agents",
      "workforce development",
      "AI productivity",
      "human-AI collaboration",
      "AI career advice",
      "boundary sensing",
      "leverage calibration",
      "enterprise AI",
      "AI leadership",
      "AI teams",
      "agentic AI",
      "AI strategy for teams"
    ]
  },
  {
    "id": "kAFVwTr4AEA",
    "title": "Silver Price is About to Do Something Wild",
    "thumbnail": "https://i.ytimg.com/vi/kAFVwTr4AEA/hqdefault.jpg",
    "channel": "Silver Dragons",
    "channel_id": "UCucqfNRyBkieAop_LDUqHEg",
    "published_at": "2026-03-01T18:00:45Z",
    "category": "Precious Metals",
    "duration_iso": "PT10M51S",
    "duration_minutes": 10.85,
    "url": "https://www.youtube.com/watch?v=kAFVwTr4AEA",
    "tags": [
      "silver price",
      "silver alert",
      "silver news",
      "silver trading",
      "silver price alert",
      "gold news",
      "gold price",
      "silver price update",
      "silver price prediction",
      "gold price prediction",
      "2026 silver price",
      "2026 silver price prediction",
      "gold price update",
      "gold update",
      "gold price forecast",
      "silver",
      "big silver news",
      "silver stacking",
      "silver investing news",
      "silver stacking news",
      "silver investing",
      "invest in silver",
      "gold",
      "coin",
      "coins",
      "buy gold",
      "silver price next",
      "silver price change",
      "silver coins"
    ]
  },
  {
    "id": "vTlW011fx9Q",
    "title": "SPECIAL REPORT: US & Israel Now At War With Iran - What Will The Implications Be? | Ryan Bohl, RANE",
    "thumbnail": "https://i.ytimg.com/vi/vTlW011fx9Q/hqdefault.jpg",
    "channel": "Adam Taggart | Thoughtful Money\u00ae",
    "channel_id": "UCjqe6xtZYTfvA4pHs0HgJsQ",
    "published_at": "2026-03-01T17:16:19Z",
    "category": "General Financial Investing and Speculation",
    "duration_iso": "PT1H7M35S",
    "duration_minutes": 67.58333333333333,
    "url": "https://www.youtube.com/watch?v=vTlW011fx9Q",
    "tags": []
  },
  {
    "id": "n4yhpxDQA84",
    "title": "URGENT: Gold & Silver Update! Key Indicators & Wartime Analysis",
    "thumbnail": "https://i.ytimg.com/vi/n4yhpxDQA84/hqdefault.jpg",
    "channel": "Bald Guy Money",
    "channel_id": "UCtPdiTVqTkg3t3PjQZqOaCA",
    "published_at": "2026-03-01T15:00:06Z",
    "category": "General Financial Investing and Speculation",
    "duration_iso": "PT16M33S",
    "duration_minutes": 16.55,
    "url": "https://www.youtube.com/watch?v=n4yhpxDQA84",
    "tags": [
      "silver",
      "silver stacker",
      "silver investment",
      "silver manipulation",
      "precious metals",
      "store of value",
      "store of wealth",
      "inflation",
      "inflation hedge",
      "invest in silver",
      "invest in gold",
      "kitco",
      "silver bullion",
      "silver coin",
      "silver eagle",
      "gold coin",
      "gold bullion",
      "gold bar",
      "federal reserve",
      "interest rates",
      "BRICS",
      "gold standard",
      "the great taking",
      "economic collapse",
      "china",
      "currency debasement",
      "bubble",
      "stock market bubble",
      "tariffs",
      "silver squeeze",
      "silver shortage",
      "confiscation",
      "iran",
      "israel",
      "war"
    ]
  },
  {
    "id": "JqGAQMYwuzQ",
    "title": "Is Cohere the Next AI Powerhouse? | First Time Founders with Ed Elson",
    "thumbnail": "https://i.ytimg.com/vi/JqGAQMYwuzQ/hqdefault.jpg",
    "channel": "The Prof G Pod \u2013 Scott Galloway",
    "channel_id": "UC1E1SVcVyU3ntWMSQEp38Yw",
    "published_at": "2026-03-01T13:00:36Z",
    "category": "General Financial Investing and Speculation",
    "duration_iso": "PT54M16S",
    "duration_minutes": 54.266666666666666,
    "url": "https://www.youtube.com/watch?v=JqGAQMYwuzQ",
    "tags": []
  }
]